pk_extractor/__init__.py
pk_extractor/cli.py
pk_extractor/generator.py
pk_extractor/logger.py
pk_extractor-0.2.3.dist-info/LICENCE
pk_extractor-0.2.3.dist-info/METADATA
pk_extractor-0.2.3.dist-info/WHEEL
pk_extractor-0.2.3.dist-info/entry_points.txt
pk_extractor-0.2.3.dist-info/RECORD
