Metadata-Version: 2.1
Name: pk-extractor
Version: 0.2.3
Summary: Project Knowledge Extractor
Author: TomoyaFujita2016
Author-email: fujita.t.2016c@gmail.com
Requires-Python: >=3.9,<4.0
Classifier: Programming Language :: Python :: 3
Classifier: Programming Language :: Python :: 3.9
Classifier: Programming Language :: Python :: 3.10
Classifier: Programming Language :: Python :: 3.11
Classifier: Programming Language :: Python :: 3.12
Classifier: Programming Language :: Python :: 3.13
Requires-Dist: gitignore-parser (>=0.1.11,<0.2.0)
Requires-Dist: tqdm (>=4.66.5,<5.0.0)
